jep_py/__init__.py
jep_py/async.py
jep_py/backend.py
jep_py/config.py
jep_py/content.py
jep_py/frontend.py
jep_py/protocol.py
jep_py/schema.py
jep_py/serializer.py
jep_py/syntax.py
jep_py/__pycache__/__init__.cpython-35.pyc
jep_py/__pycache__/async.cpython-35.pyc
jep_py/__pycache__/backend.cpython-35.pyc
jep_py/__pycache__/config.cpython-35.pyc
jep_py/__pycache__/content.cpython-35.pyc
jep_py/__pycache__/frontend.cpython-35.pyc
jep_py/__pycache__/protocol.cpython-35.pyc
jep_py/__pycache__/schema.cpython-35.pyc
jep_py/__pycache__/serializer.cpython-35.pyc
jep_py/__pycache__/syntax.cpython-35.pyc
jep_python-0.5.5.dist-info/DESCRIPTION.rst
jep_python-0.5.5.dist-info/METADATA
jep_python-0.5.5.dist-info/RECORD
jep_python-0.5.5.dist-info/WHEEL
jep_python-0.5.5.dist-info/metadata.json
jep_python-0.5.5.dist-info/top_level.txt
test/__init__.py
test/logconfig.py
test/test_backend.py
test/test_config.py
test/test_content.py
test/test_frontend.py
test/test_integration.py
test/test_protocol.py
test/test_schema.py
test/test_serializer.py
test/test_syntax_.py
test/__pycache__/__init__.cpython-35.pyc
test/__pycache__/logconfig.cpython-35.pyc
test/__pycache__/test_backend.cpython-35-PYTEST.pyc
test/__pycache__/test_config.cpython-35-PYTEST.pyc
test/__pycache__/test_content.cpython-35-PYTEST.pyc
test/__pycache__/test_frontend.cpython-35-PYTEST.pyc
test/__pycache__/test_integration.cpython-35-PYTEST.pyc
test/__pycache__/test_protocol.cpython-35-PYTEST.pyc
test/__pycache__/test_schema.cpython-35-PYTEST.pyc
test/__pycache__/test_serializer.cpython-35-PYTEST.pyc
test/__pycache__/test_syntax_.cpython-35-PYTEST.pyc
