Metadata-Version: 2.0
Name: jep-python
Version: 0.5.5
Summary: Python implementation of the Joint Editors Protocol.
Home-page: https://github.com/jep-project/jep-python
Author: Mike Pagel
Author-email: mike@mpagel.de
License: UNKNOWN
Keywords: jep dsl language editor
Platform: UNKNOWN
Classifier: Development Status :: 4 - Beta
Classifier: Intended Audience :: Developers
Classifier: Topic :: Software Development :: Libraries
Classifier: License :: OSI Approved :: MIT License
Classifier: Programming Language :: Python :: 3.3
Classifier: Programming Language :: Python :: 3.4
Classifier: Programming Language :: Python :: 3.5
Requires-Dist: u-msgpack-python
